cared/__init__.py
cared/py.typed
cared-0.1.1.dist-info/METADATA
cared-0.1.1.dist-info/WHEEL
cared-0.1.1.dist-info/entry_points.txt
cared-0.1.1.dist-info/licenses/LICENSE
cared-0.1.1.dist-info/RECORD
