Metadata-Version: 2.3
Name: cared
Version: 0.1.1
Summary: Dummy Python package to block the name cared on pypi and avoid name squatting attacks.
Project-URL: Documentation, https://github.com/likat-rostock/cared
Project-URL: GitHub, https://github.com/likat-rostock/cared
Author-email: David Linke <david.linke@catalysis.de>
Maintainer-email: David Linke <david.linke@catalysis.de>
License: Apache 2.0
License-File: LICENSE
Keywords: CaReD
Classifier: Development Status :: 5 - Production/Stable
Classifier: Environment :: Console
Classifier: Intended Audience :: Science/Research
Classifier: License :: OSI Approved :: Apache Software License
Classifier: Operating System :: OS Independent
Classifier: Programming Language :: Python
Classifier: Programming Language :: Python :: 3.10
Classifier: Programming Language :: Python :: 3.11
Classifier: Programming Language :: Python :: 3.12
Requires-Python: >=3.10
Provides-Extra: dev
Requires-Dist: pytest; extra == 'dev'
